{
  "entityType" : "RULE_CHAIN",
  "entity" : {
    "additionalInfo" : null,
    "configuration" : null,
    "debugMode" : false,
    "externalId" : null,
    "firstRuleNodeId" : {
      "entityType" : "RULE_NODE",
      "id" : "96b5dd60-30e1-11ee-ab78-536eaffa7025"
    },
    "id" : {
      "entityType" : "RULE_CHAIN",
      "id" : "96abf250-30e1-11ee-ab78-536eaffa7025"
    },
    "name" : "Edge Root Rule Chain",
    "root" : true,
    "type" : "EDGE"
  },
  "metaData" : {
    "connections" : [ {
      "fromIndex" : 0,
      "toIndex" : 3,
      "type" : "Success"
    }, {
      "fromIndex" : 1,
      "toIndex" : 7,
      "type" : "Success"
    }, {
      "fromIndex" : 2,
      "toIndex" : 7,
      "type" : "Success"
    }, {
      "fromIndex" : 3,
      "toIndex" : 1,
      "type" : "Post telemetry"
    }, {
      "fromIndex" : 3,
      "toIndex" : 2,
      "type" : "Post attributes"
    }, {
      "fromIndex" : 3,
      "toIndex" : 4,
      "type" : "RPC Request from Device"
    }, {
      "fromIndex" : 3,
      "toIndex" : 5,
      "type" : "Other"
    }, {
      "fromIndex" : 3,
      "toIndex" : 6,
      "type" : "RPC Request to Device"
    }, {
      "fromIndex" : 3,
      "toIndex" : 8,
      "type" : "Attributes Deleted"
    }, {
      "fromIndex" : 3,
      "toIndex" : 8,
      "type" : "Attributes Updated"
    }, {
      "fromIndex" : 4,
      "toIndex" : 9,
      "type" : "Success"
    } ],
    "firstNodeIndex" : 0,
    "nodes" : [ {
      "additionalInfo" : {
        "description" : "Process incoming messages from devices with the alarm rules defined in the device profile. Dispatch all incoming messages with \"Success\" relation type.",
        "layoutX" : 187,
        "layoutY" : 468
      },
      "configuration" : {
        "persistAlarmRulesState" : false,
        "fetchAlarmRulesStateOnStart" : false
      },
      "createdTime" : 0,
      "debugMode" : false,
      "externalId" : null,
      "id" : {
        "entityType" : "RULE_NODE",
        "id" : "96b5dd60-30e1-11ee-ab78-536eaffa7025"
      },
      "name" : "Device Profile Node",
      "ruleChainId" : null,
      "singletonMode" : false,
      "type" : "org.thingsboard.rule.engine.profile.TbDeviceProfileNode"
    }, {
      "additionalInfo" : {
        "layoutX" : 823,
        "layoutY" : 157
      },
      "configuration" : {
        "defaultTTL" : 0
      },
      "createdTime" : 0,
      "debugMode" : false,
      "externalId" : null,
      "id" : {
        "entityType" : "RULE_NODE",
        "id" : "96be68e0-30e1-11ee-ab78-536eaffa7025"
      },
      "name" : "Save Timeseries",
      "ruleChainId" : null,
      "singletonMode" : false,
      "type" : "org.thingsboard.rule.engine.telemetry.TbMsgTimeseriesNode"
    }, {
      "additionalInfo" : {
        "layoutX" : 824,
        "layoutY" : 52
      },
      "configuration" : {
        "scope" : "CLIENT_SCOPE",
        "notifyDevice" : "false"
      },
      "createdTime" : 0,
      "debugMode" : false,
      "externalId" : null,
      "id" : {
        "entityType" : "RULE_NODE",
        "id" : "96c08bc0-30e1-11ee-ab78-536eaffa7025"
      },
      "name" : "Save Client Attributes",
      "ruleChainId" : null,
      "singletonMode" : false,
      "type" : "org.thingsboard.rule.engine.telemetry.TbMsgAttributesNode"
    }, {
      "additionalInfo" : {
        "layoutX" : 347,
        "layoutY" : 149
      },
      "configuration" : {
        "version" : 0
      },
      "createdTime" : 0,
      "debugMode" : false,
      "externalId" : null,
      "id" : {
        "entityType" : "RULE_NODE",
        "id" : "96c19d30-30e1-11ee-ab78-536eaffa7025"
      },
      "name" : "Message Type Switch",
      "ruleChainId" : null,
      "singletonMode" : false,
      "type" : "org.thingsboard.rule.engine.filter.TbMsgTypeSwitchNode"
    }, {
      "additionalInfo" : {
        "layoutX" : 825,
        "layoutY" : 266
      },
      "configuration" : {
        "scriptLang" : "TBEL",
        "jsScript" : "return '\\nIncoming message:\\n' + JSON.stringify(msg) + '\\nIncoming metadata:\\n' + JSON.stringify(metadata);",
        "tbelScript" : "return '\\nIncoming message:\\n' + JSON.stringify(msg) + '\\nIncoming metadata:\\n' + JSON.stringify(metadata);"
      },
      "createdTime" : 0,
      "debugMode" : false,
      "externalId" : null,
      "id" : {
        "entityType" : "RULE_NODE",
        "id" : "96c4f890-30e1-11ee-ab78-536eaffa7025"
      },
      "name" : "Log RPC from Device",
      "ruleChainId" : null,
      "singletonMode" : false,
      "type" : "org.thingsboard.rule.engine.action.TbLogNode"
    }, {
      "additionalInfo" : {
        "layoutX" : 824,
        "layoutY" : 378
      },
      "configuration" : {
        "scriptLang" : "TBEL",
        "jsScript" : "return '\\nIncoming message:\\n' + JSON.stringify(msg) + '\\nIncoming metadata:\\n' + JSON.stringify(metadata);",
        "tbelScript" : "return '\\nIncoming message:\\n' + JSON.stringify(msg) + '\\nIncoming metadata:\\n' + JSON.stringify(metadata);"
      },
      "createdTime" : 0,
      "debugMode" : false,
      "externalId" : null,
      "id" : {
        "entityType" : "RULE_NODE",
        "id" : "96c546b0-30e1-11ee-ab78-536eaffa7025"
      },
      "name" : "Log Other",
      "ruleChainId" : null,
      "singletonMode" : false,
      "type" : "org.thingsboard.rule.engine.action.TbLogNode"
    }, {
      "additionalInfo" : {
        "layoutX" : 824,
        "layoutY" : 466
      },
      "configuration" : {
        "timeoutInSeconds" : 60
      },
      "createdTime" : 0,
      "debugMode" : false,
      "externalId" : null,
      "id" : {
        "entityType" : "RULE_NODE",
        "id" : "96c98c70-30e1-11ee-ab78-536eaffa7025"
      },
      "name" : "RPC Call Request",
      "ruleChainId" : null,
      "singletonMode" : false,
      "type" : "org.thingsboard.rule.engine.rpc.TbSendRPCRequestNode"
    }, {
      "additionalInfo" : {
        "layoutX" : 1126,
        "layoutY" : 104
      },
      "configuration" : {
        "scope" : "SERVER_SCOPE"
      },
      "createdTime" : 0,
      "debugMode" : false,
      "externalId" : null,
      "id" : {
        "entityType" : "RULE_NODE",
        "id" : "96c9da90-30e1-11ee-ab78-536eaffa7025"
      },
      "name" : "Push to cloud",
      "ruleChainId" : null,
      "singletonMode" : false,
      "type" : "org.thingsboard.rule.engine.edge.TbMsgPushToCloudNode"
    }, {
      "additionalInfo" : {
        "layoutX" : 826,
        "layoutY" : 601
      },
      "configuration" : {
        "scope" : "SERVER_SCOPE"
      },
      "createdTime" : 0,
      "debugMode" : false,
      "externalId" : null,
      "id" : {
        "entityType" : "RULE_NODE",
        "id" : "96ca76d0-30e1-11ee-ab78-536eaffa7025"
      },
      "name" : "Push to cloud",
      "ruleChainId" : null,
      "singletonMode" : false,
      "type" : "org.thingsboard.rule.engine.edge.TbMsgPushToCloudNode"
    }, {
      "additionalInfo" : {
        "description" : "",
        "layoutX" : 1179,
        "layoutY" : 263
      },
      "configuration" : {
        "detailsList" : [ "TITLE" ],
        "addToMetadata" : false
      },
      "createdTime" : 0,
      "debugMode" : false,
      "externalId" : null,
      "id" : {
        "entityType" : "RULE_NODE",
        "id" : "26303aa0-31e9-11ee-ab78-536eaffa7025"
      },
      "name" : "details",
      "ruleChainId" : null,
      "singletonMode" : false,
      "type" : "org.thingsboard.rule.engine.metadata.TbGetTenantDetailsNode"
    } ],
    "ruleChainConnections" : null
  },
  "relations" : [ ],
  "attributes" : {
    "SERVER_SCOPE" : [ ]
  }
}